horst/__init__.py
horst/horst.py
horst/horst_c.py
horst/horst_l.py
horst/horst_p.py
horst-0.3.16.dist-info/LICENSE
horst-0.3.16.dist-info/METADATA
horst-0.3.16.dist-info/WHEEL
horst-0.3.16.dist-info/entry_points.txt
horst-0.3.16.dist-info/top_level.txt
horst-0.3.16.dist-info/RECORD
