Metadata-Version: 2.1
Name: horst
Version: 0.3.16
Summary: Do not repeat yourself in SQL scripts by listing the same fields again and again.
Home-page: https://gitlab.com/FMG_ULM/horst
Author: Frank T. Maas
Author-email: frank.maas@funkemedien.de
License: UNKNOWN
Platform: UNKNOWN
Classifier: Programming Language :: Python :: 3
Classifier: License :: OSI Approved :: MIT License
Classifier: Operating System :: OS Independent
License-File: LICENSE
Requires-Dist: sly
